{
  "_fv": 24,
  "_type": "recipe",
  "definition": {
    "recipeType": "Crafting",
    "xpReward": 0.0,
    "cookingTime": 200,
    "recipeRetstackSize": 1,
    "recipeShapeless": true,
    "recipeSlots": [
      {
        "value": "CUSTOM:BloodyGlowstoneDust"
      },
      {
        "value": "CUSTOM:BloodyGlowstoneDust"
      },
      {
        "value": ""
      },
      {
        "value": "CUSTOM:BloodyGlowstoneDust"
      },
      {
        "value": "CUSTOM:BloodyGlowstoneDust"
      },
      {
        "value": ""
      },
      {
        "value": ""
      },
      {
        "value": ""
      },
      {
        "value": ""
      }
    ],
    "recipeReturnStack": {
      "value": "CUSTOM:BloodyGlowstone"
    },
    "name": "ancientbloodyglowstoner",
    "namespace": "mod"
  }
}