{
  "_fv": 24,
  "_type": "recipe",
  "definition": {
    "recipeType": "Crafting",
    "xpReward": 0.0,
    "cookingTime": 200,
    "recipeRetstackSize": 1,
    "group": "",
    "recipeShapeless": false,
    "recipeSlots": [
      {
        "value": "CUSTOM:XpBottleOfInfinity"
      },
      {
        "value": "CUSTOM:MagicBottle"
      },
      {
        "value": "CUSTOM:XpBottleOfInfinity"
      },
      {
        "value": "CUSTOM:MagicBottle"
      },
      {
        "value": "CUSTOM:XpLordHeart"
      },
      {
        "value": "CUSTOM:MagicBottle"
      },
      {
        "value": "CUSTOM:XpBottleOfInfinity"
      },
      {
        "value": "Blocks.OBSIDIAN"
      },
      {
        "value": "CUSTOM:XpBottleOfInfinity"
      }
    ],
    "recipeReturnStack": {
      "value": "CUSTOM:XpBlockOfInfinity"
    },
    "name": "xpblockofinfinityr",
    "namespace": "mod"
  }
}